Administrative/__init__.py
Figit_Administrative-1.0.0.dist-info/METADATA
Figit_Administrative-1.0.0.dist-info/WHEEL
Figit_Administrative-1.0.0.dist-info/top_level.txt
Figit_Administrative-1.0.0.dist-info/RECORD
