Metadata-Version: 2.1
Name: Figit-Administrative
Version: 1.0.0
Summary: Opens files with administrative permissions.
